django_view_generator/__init__.py
django_view_generator/utils.py
django_view_generator/management/__init__.py
django_view_generator/management/commands/__init__.py
django_view_generator/management/commands/generate_views_and_serializers.py
my_django_generator-0.1.0.dist-info/LICENCE
my_django_generator-0.1.0.dist-info/METADATA
my_django_generator-0.1.0.dist-info/WHEEL
my_django_generator-0.1.0.dist-info/entry_points.txt
my_django_generator-0.1.0.dist-info/top_level.txt
my_django_generator-0.1.0.dist-info/RECORD
